<annotation>
	<folder>XML</folder>
	<filename>new_923.jpg</filename>
	<path>F:\Object-Detection\Scripts\converters\labels\train\new_923.jpg</path>
	<source>
		<database>Unknown</database>
	</source>
	<size>
		<width>1280</width>
		<height>720</height>
		<depth>3</depth>
	</size>
	<segmented>0</segmented>
	<object>
		<name>Cam di nguoc chieu</name>
		<pose>Unspecified</pose>
		<truncated>0</truncated>
		<difficult>0</difficult>
		<bndbox>
			<xmin>2</xmin>
			<ymin>23</ymin>
			<xmax>58</xmax>
			<ymax>102</ymax>
		</bndbox>
	</object>
	<object>
		<name>Huong di phai re phai</name>
		<pose>Unspecified</pose>
		<truncated>0</truncated>
		<difficult>0</difficult>
		<bndbox>
			<xmin>0</xmin>
			<ymin>105</ymin>
			<xmax>44</xmax>
			<ymax>189</ymax>
		</bndbox>
	</object>
	<object>
		<name>Cam do xe</name>
		<pose>Unspecified</pose>
		<truncated>0</truncated>
		<difficult>0</difficult>
		<bndbox>
			<xmin>928</xmin>
			<ymin>167</ymin>
			<xmax>969</xmax>
			<ymax>217</ymax>
		</bndbox>
	</object>
	<object>
		<name>Bien khac</name>
		<pose>Unspecified</pose>
		<truncated>0</truncated>
		<difficult>0</difficult>
		<bndbox>
			<xmin>1112</xmin>
			<ymin>144</ymin>
			<xmax>1160</xmax>
			<ymax>197</ymax>
		</bndbox>
	</object>
</annotation>
