<annotation>
	<folder>XML</folder>
	<filename>new_1480.jpg</filename>
	<path>F:\Object-Detection\Scripts\converters\labels\val\new_1480.jpg</path>
	<source>
		<database>Unknown</database>
	</source>
	<size>
		<width>1280</width>
		<height>720</height>
		<depth>3</depth>
	</size>
	<segmented>0</segmented>
	<object>
		<name>Huong di phai re phai</name>
		<pose>Unspecified</pose>
		<truncated>0</truncated>
		<difficult>0</difficult>
		<bndbox>
			<xmin>92</xmin>
			<ymin>60</ymin>
			<xmax>150</xmax>
			<ymax>126</ymax>
		</bndbox>
	</object>
	<object>
		<name>Cam di nguoc chieu</name>
		<pose>Unspecified</pose>
		<truncated>0</truncated>
		<difficult>0</difficult>
		<bndbox>
			<xmin>102</xmin>
			<ymin>1</ymin>
			<xmax>168</xmax>
			<ymax>55</ymax>
		</bndbox>
	</object>
	<object>
		<name>Cam do xe</name>
		<pose>Unspecified</pose>
		<truncated>0</truncated>
		<difficult>0</difficult>
		<bndbox>
			<xmin>910</xmin>
			<ymin>212</ymin>
			<xmax>955</xmax>
			<ymax>258</ymax>
		</bndbox>
	</object>
</annotation>
